LICENSE
MANIFEST.in
README.rst
setup.cfg
setup.py
inmofactory/__init__.py
inmofactory/__init__.pyc
inmofactory/api.py
inmofactory_api_python.egg-info/PKG-INFO
inmofactory_api_python.egg-info/SOURCES.txt
inmofactory_api_python.egg-info/dependency_links.txt
inmofactory_api_python.egg-info/requires.txt
inmofactory_api_python.egg-info/top_level.txt