Metadata-Version: 1.1
Name: inmofactory-api-python
Version: 0.1.2
Summary: Upload properties to Inmofactory using INMOFACTORY API.
Home-page: https://bitbucket.org/abalt/inmofactory-api-python
Author: DNest
Author-email: admin@dnestagency.com
License: Copyright (c) 2011, Tangent Communications PLC and individual contributors.
